inifix/__init__.py
inifix/_floatencoder.py
inifix/_format.py
inifix/_io.py
inifix/_typing.py
inifix/_validation.py
inifix/_version.py
inifix/format.py
inifix/py.typed
inifix-6.1.1.dist-info/METADATA
inifix-6.1.1.dist-info/WHEEL
inifix-6.1.1.dist-info/licenses/LICENSE
inifix-6.1.1.dist-info/RECORD
