Metadata-Version: 2.4
Name: inifix
Version: 6.1.1
Summary: An I/O library for Pluto-style ini files.
Project-URL: Homepage, https://github.com/neutrinoceros/inifix
Project-URL: Changelog, https://github.com/neutrinoceros/inifix/blob/main/CHANGELOG.md
Author: C.M.T. Robert
License: GPL-3.0
License-File: LICENSE
Classifier: License :: OSI Approved :: GNU General Public License v3 (GPLv3)
Classifier: Programming Language :: Python :: 3
Classifier: Typing :: Typed
Requires-Python: >=3.10
Requires-Dist: exceptiongroup>=1.0.0; python_full_version < '3.11'
Requires-Dist: typing-extensions>=4.2.0; python_full_version < '3.11'
